{
  "brand_name": "Čia Market",
  "mission_vision": null,
  "sponsorship_activities": [],
  "channels": [
    {
      "channel_type": "Online",
      "specifics": [
        "Website"
      ]
    }
  ],
  "industry": {
    "Primary_Industry": "Retail",
    "Secondary_Industry": "Supermarkets"
  },
  "regions": [
    "Lithuania"
  ],
  "interests": [],
  "audience_lifestyle": null,
  "languages": null,
  "business_model_canvas": {
    "Key_Partners": [],
    "Key_Activities": [],
    "Value_Propositions": [],
    "Customer_Relationships": [],
    "Customer_Segments": [],
    "Channels": [],
    "Cost_Structure": [],
    "Revenue_Streams": []
  },
  "link": "https://en.wikipedia.org/wiki/%C4%8Cia_Market",
  "parsed_at": "2024-10-01T14:38:53.561803Z",
  "country": "Lithuanian brands",
  "category": "General",
  "body_text": "From Wikipedia, the free encyclopedia Lithuanian supermarket chain Čia Market, UAB Native name Čia Market Industry Retail Founded 1996 ( 1996 ) Headquarters Telšiai , Lithuania Area served Lithuania Key people CEO Aurelijus Vaitiekus Revenue € 48.321 million [ 1 ] Operating income - €0.420 million Net income - €0.414 million Total assets €4.553 million Total equity - €0.482 million Number of employees 561 (2022) Website www .ciamarket .lt Čia Market shop in Druskininkai Čia Market from side Čia Market is a supermarket chain in Lithuania . In 2022, it was 10th largest chain of retail stores in Lithuania. In 2018, company had around €0.9 million in financial loses while having around €54 million in turnover. [ 2 ] [ 3 ] In 2019, the employees of the Čia Market shop in Panevėžys could not stand any longer and complained to the food quality inspectors about the possible large-scale cheating of customers. Some of the products were expired for 2 years. [ 4 ] In 2020, due to financial losses the company closed 24 shops. [ 5 ] In 2022 company expected to reach €48 million in revenue. [ 6 ] History [ edit ] UAB \"Čia Market\" is a company from Samogitia region. At first it was named \"Žemaitijos prekyba\" and it only was selling dairy products . In 2011 the company changed its name to \"Čia Market\". [ 7 ] List of supermarket chains in Lithuania This Lithuanian corporation or company article is a stub . You can help Wikipedia by expanding it . v t e Retrieved from \" https://en.wikipedia.org/w/index.php?title=Čia_Market&oldid=1188000252 \" Categories : Supermarkets of Lithuania Retail companies established in 1996 Lithuanian brands Lithuanian company stubs Hidden categories: Articles with short description Short description matches Wikidata All stub articles",
  "infobox": {
    "logo_url": "https://upload.wikimedia.org/wikipedia/commons/thumb/2/2a/%C4%8Cia_Market_logo.png/125px-%C4%8Cia_Market_logo.png",
    "name": "",
    "native_name": "Čia Market",
    "industry": "Retail",
    "founded": "1996 ( 1996 )",
    "headquarters": "Telšiai , Lithuania",
    "area_served": "Lithuania",
    "key_people": "CEO Aurelijus Vaitiekus",
    "revenue": "€ 48.321 million [ 1 ]",
    "operating_income": "- €0.420 million",
    "net_income": "- €0.414 million",
    "total_assets": "€4.553 million",
    "total_equity": "- €0.482 million",
    "number_of_employees": "561 (2022)",
    "website": "www .ciamarket .lt"
  },
  "company_name": "Unknown",
  "logo_url": "https://upload.wikimedia.org/wikipedia/commons/thumb/2/2a/%C4%8Cia_Market_logo.png/125px-%C4%8Cia_Market_logo.png"
}