{
  "brand_name": "Nabtesco Corporation",
  "mission_vision": null,
  "sponsorship_activities": [],
  "channels": [],
  "industry": {
    "Primary_Industry": "Machinery",
    "Secondary_Industry": "Robotics"
  },
  "regions": [
    "Worldwide"
  ],
  "interests": [
    {
      "category": "Technology and Science Interests",
      "specifics": [
        "Robotics",
        "Engineering"
      ]
    }
  ],
  "audience_lifestyle": null,
  "languages": [
    "Japanese",
    "English"
  ],
  "business_model_canvas": {
    "Key_Partners": [],
    "Key_Activities": [],
    "Value_Propositions": [],
    "Customer_Relationships": [],
    "Customer_Segments": [],
    "Channels": [],
    "Cost_Structure": [],
    "Revenue_Streams": []
  },
  "link": "https://en.wikipedia.org/wiki/Nabtesco",
  "parsed_at": "2024-10-01T14:38:43.539700Z",
  "country": "Japanese brands",
  "category": "General",
  "body_text": "From Wikipedia, the free encyclopedia Japanese engineering company Nabtesco Corporation Native name ナブテスコ株式会社 Company type Public ( K.K ) Traded as TYO : 6268 ISIN JP3651210001 Industry Machinery Founded September 29, 2003 ; 21 years ago ( 2003-09-29 ) Headquarters Hirakawachō , Chiyoda-ku, Tokyo 102-0093 , Japan Area served Worldwide Key people Katsuhiro Teramoto ( President and CEO ) Products Industrial robot parts Railway car parts Aircraft parts Flight control systems Automatic door systems Revenue JPY 294.6 billion ( US$ 2.7 billion) ( FY 2017) Net income JPY 21 billion (US$ 192 million) (FY 2017) Number of employees 7,713 (consolidated, December 31, 2018) Website Official website Footnotes / references [ 1 ] [ 2 ] [ 3 ] JA Kyosai Building, where the headquarters of Nabtesco is located Nabtesco ( ナブテスコ株式会社 , Nabutesuko Kabushiki-gaisha ) is a Japanese engineering company that specializes in gearboxes, rotors, motors and robotics. History [ edit ] The company was founded in 2003 and has several subsidiaries. [ 4 ] In 2010, the company acquired the Business Segment Door Automation division of the Swiss company Dormakaba . [ 5 ] Management [ edit ] Since 2017, Kazuaki Kotani has served as chairman and Katsuhiro Teramoto has served as president of Nabtesco. [ 5 ] Products [ edit ] The company manufactures cycloidal drives , railway brakes and platform screen doors . [ 4 ] Official Website (in English) Retrieved from \" https://en.wikipedia.org/w/index.php?title=Nabtesco&oldid=1218059511 \" Categories : Companies of Japan Manufacturing companies based in Tokyo Companies listed on the Tokyo Stock Exchange Japanese companies established in 2003 Manufacturing companies established in 2003 Robotics companies of Japan Industrial robotics Japanese brands Hidden categories: Articles with short description Short description matches Wikidata Use mdy dates from April 2019 Articles containing Japanese-language text Official website different in Wikidata and Wikipedia",
  "infobox": {
    "logo_url": "https://upload.wikimedia.org/wikipedia/commons/thumb/7/78/Nabtesco_company_logo.svg/250px-Nabtesco_company_logo.svg.png",
    "name": "Footnotes / references [ 1 ] [ 2 ] [ 3 ]",
    "native_name": "ナブテスコ株式会社",
    "company_type": "Public ( K.K )",
    "traded_as": "TYO : 6268",
    "isin": "JP3651210001",
    "industry": "Machinery",
    "founded": "September 29, 2003 ; 21 years ago ( 2003-09-29 )",
    "headquarters": "Hirakawachō , Chiyoda-ku, Tokyo 102-0093 , Japan",
    "area_served": "Worldwide",
    "key_people": "Katsuhiro Teramoto ( President and CEO )",
    "products": "Industrial robot parts Railway car parts Aircraft parts Flight control systems Automatic door systems",
    "revenue": "JPY 294.6 billion\n                      ( US$ 2.7 billion) ( FY 2017)",
    "net_income": "JPY 21 billion\n                      (US$ 192 million) (FY 2017)",
    "number_of_employees": "7,713 (consolidated, December 31, 2018)",
    "website": "Official website"
  },
  "company_name": "Footnotes / references [ 1 ] [ 2 ] [ 3 ]",
  "logo_url": "https://upload.wikimedia.org/wikipedia/commons/thumb/7/78/Nabtesco_company_logo.svg/250px-Nabtesco_company_logo.svg.png"
}