{
  "brand_name": "Nonghyup Bank",
  "mission_vision": null,
  "sponsorship_activities": [],
  "channels": [],
  "industry": {
    "Primary_Industry": "Banking",
    "Secondary_Industry": "Financial Services"
  },
  "regions": [
    "South Korea"
  ],
  "interests": [
    {
      "category": "Professional and Educational Interests",
      "specifics": [
        "Financial Services",
        "Banking"
      ]
    }
  ],
  "audience_lifestyle": null,
  "languages": [
    "Korean",
    "English"
  ],
  "business_model_canvas": {
    "Key_Partners": [],
    "Key_Activities": [],
    "Value_Propositions": [],
    "Customer_Relationships": [],
    "Customer_Segments": [],
    "Channels": [],
    "Cost_Structure": [],
    "Revenue_Streams": []
  },
  "link": "https://en.wikipedia.org/wiki/Nonghyup_Bank",
  "parsed_at": "2024-10-01T14:39:52.024691Z",
  "country": "South Korean brands",
  "category": "General",
  "body_text": "From Wikipedia, the free encyclopedia South Korean agricultural bank Nonghyup Bank (NHBank) Native name NH농협은행 Company type Private Industry Banking Founded March 12, 2012 ; 12 years ago ( 2012-03-12 ) Headquarters Seoul , South Korea Area served South Korea Key people Lee Seok-young (CEO) Revenue KRW 17.837 trillion (2022) Operating income KRW 2.78 trillion (2022) Net income KRW 1.8 trillion (2022) Total assets KRW 2.38 trillion (2022) Members 16,186 Number of employees 16,163 (2022) Korean name Hangul 농협 은행 Hanja 農協 銀行 Revised Romanization Nonghyup Eunhaeng McCune–Reischauer Nonghyŏp Ŭnhaeng Website www.nhbank.com Nonghyup Bank or NH Bank ( Korean : 농협은행 , SWIFT : NACFKRSE) is a specialized agricultural bank in Korea and is in charge of financial services, headquartered in Jung-gu , Seoul , South Korea . The bank was established by the split-off of the credit and banking business from National Agricultural Cooperative Federation (“NACF”) on March 2, 2012. It is now owned by the Nonghyup Financial Group. The predecessor of Nonghyup Bank started as Agricultural Bank established in 1907 as a financial association. Unlike other major commercial Korean bank, Nonghyup bank is established with 100% domestic capital. [ 1 ] Nonghyup bank has 1,106 branches in domestic area, and 12 branches outside Korea, including New York, Beijing, Hanoi. It has the largest number of branches in Korea. [ 2 ] On 29 April 2021, Nonghyup Bank was granted a Hong Kong banking licence. [ 3 ] History [ edit ] 1907: Establishment of a financial association 1958: Agricultural Bank launched based on financial cooperatives 1961: Agricultural Bank and Nonghyup were merged, and the urban branch of Agricultural Bank was separated into Small and Medium Business Bank. 2000: Merger of the National Agricultural Cooperative Federation, National Livestock Cooperative Federation, and National Ginseng Federation of Korea 2012: Nonghyup National Association's credit business was separated into NH Nonghyup Financial Group and launched as a subsidiary. Economy of South Korea List of Banks in South Korea National Agricultural Cooperative Federation Nonghyup's Korean Homepage This Asian bank-related article is a stub . You can help Wikipedia by expanding it . v t e This article about a South Korean company is a stub . You can help Wikipedia by expanding it . v t e Retrieved from \" https://en.wikipedia.org/w/index.php?title=Nonghyup_Bank&oldid=1247088918 \" Categories : Banks of South Korea Companies based in Seoul South Korean brands Government-owned banks of South Korea South Korean companies established in 2012 Banks established in 2012 Asian bank stubs South Korean company stubs Hidden categories: Articles with short description Short description is different from Wikidata Articles containing Korean-language text All stub articles",
  "infobox": {
    "native_name": "NH농협은행",
    "company_type": "Private",
    "industry": "Banking",
    "founded": "March 12, 2012 ; 12 years ago ( 2012-03-12 )",
    "headquarters": "Seoul , South Korea",
    "area_served": "South Korea",
    "key_people": "Lee Seok-young (CEO)",
    "revenue": "KRW 17.837 trillion (2022)",
    "operating_income": "KRW 2.78 trillion (2022)",
    "net_income": "KRW 1.8 trillion (2022)",
    "total_assets": "KRW 2.38 trillion (2022)",
    "members": "16,186",
    "number_of_employees": "16,163 (2022)",
    "name": "",
    "hangul": "농협 은행",
    "hanja": "農協 銀行",
    "revised_romanization": "Nonghyup Eunhaeng",
    "mccune_reischauer": "Nonghyŏp Ŭnhaeng",
    "website": "www.nhbank.com"
  },
  "company_name": "Unknown",
  "logo_url": "No logo available"
}