{
  "brand_name": "Parco Co., Ltd.",
  "mission_vision": null,
  "sponsorship_activities": [],
  "channels": [
    {
      "channel_type": "Retail",
      "specifics": [
        "PARCO Urban Stores",
        "PARCO Community Stores",
        "Zero Gate complexes"
      ]
    },
    {
      "channel_type": "Online",
      "specifics": [
        "Website"
      ]
    }
  ],
  "industry": {
    "Primary_Industry": "Retail",
    "Secondary_Industry": "Real Estate"
  },
  "regions": [
    "Japan"
  ],
  "interests": [],
  "audience_lifestyle": null,
  "languages": [
    "Japanese",
    "English"
  ],
  "business_model_canvas": {
    "Key_Partners": [
      "J. Front Retailing"
    ],
    "Key_Activities": [
      "Retail Operations",
      "Property Management",
      "Consultant Projects"
    ],
    "Value_Propositions": [
      "Diverse Shopping Experience",
      "Hybrid Business Model"
    ],
    "Customer_Relationships": [
      "In-store Experience",
      "Online Shopping"
    ],
    "Customer_Segments": [
      "Local Shoppers",
      "Tourists"
    ],
    "Channels": [
      "Physical Stores",
      "Online Store"
    ],
    "Cost_Structure": [
      "Operational Costs",
      "Marketing Expenses"
    ],
    "Revenue_Streams": [
      "Retail Sales",
      "Property Management Fees"
    ]
  },
  "link": "https://en.wikipedia.org/wiki/Parco_(retailer)",
  "parsed_at": "2024-10-01T14:38:04.491203Z",
  "country": "Japanese brands",
  "category": "General",
  "body_text": "From Wikipedia, the free encyclopedia Department store chain You can help expand this article with text translated from the corresponding article in Japanese . (April 2024) Click [show] for important translation instructions. View a machine-translated version of the Japanese article. Machine translation, like DeepL or Google Translate , is a useful starting point for translations, but translators must revise errors as necessary and confirm that the translation is accurate, rather than simply copy-pasting machine-translated text into the English Wikipedia. Consider adding a topic to this template: there are already 1,162 articles in the main category , and specifying |topic= will aid in categorization. Do not translate text that appears unreliable or low-quality. If possible, verify the text with references provided in the foreign-language article. You must provide copyright attribution in the edit summary accompanying your translation by providing an interlanguage link to the source of your translation. A model attribution edit summary is Content in this edit is translated from the existing Japanese Wikipedia article at [[:ja:パルコ]]; see its history for attribution. You may also add the template {{Translated|ja|パルコ}} to the talk page . For more guidance, see Wikipedia:Translation . Parco Co., Ltd. Native name 株式会社パルコ Company type Subsidiary Industry Retail Founded Ikebukuro, Toshima, Tokyo , Japan February 13, 1953 ( 1953-02-13 ) Headquarters Shibuya First Place Building, 8-16, Shinsencho, Shibuya, Tokyo , Japan 1-28-2, Minami- Ikebukuro , Toshima, Tokyo , Japan (registered) Number of locations 17 stores (2023) Key people Kozo Makiyama (President) Revenue ¥ 264,840 million (FY2010) [ 1 ] Operating income ¥ 9,218 million (FY2010) [ 1 ] Net income ¥ 4,400 million (FY2010) [ 1 ] Total assets ¥ 222,135 million (FY2010) [ 1 ] Total equity ¥ 81,868 million (FY2010) [ 1 ] Owner J. Front Retailing Number of employees 651 (directly) 2,208 (contract) Website www .parco .co .jp /en / Parco Co., Ltd. ( 株式会社パルコ , Kabushiki-gaisha Paruko ) is a chain of department stores primarily in Japan. The first store was established in Tokyo on February 13, 1953 ; 71 years ago ( 1953-02-13 ) , and since then the company has opened stores in cities all over Japan. The PARCO Group primarily conducts business through its Shopping Complex Business segment, which includes its PARCO Urban Stores, PARCO Community Stores, and Zero Gate complexes. Zero Gate complexes serve as platforms for other retail establishments. Oita Parco PARCO is currently implementing a hybrid business model that combines retail businesses and real estate . PARCO Group also undertakes property management and consultant projects on a contract basis. Media related to Parco (retailer) at Wikimedia Commons This article about a Japanese corporation- or company-related topic is a stub . You can help Wikipedia by expanding it . v t e This retail business article is a stub . You can help Wikipedia by expanding it . v t e Retrieved from \" https://en.wikipedia.org/w/index.php?title=Parco_(retailer)&oldid=1220132084 \" Categories : Retail companies established in 1953 Japanese companies established in 1953 Retail companies based in Tokyo Companies formerly listed on the Tokyo Stock Exchange Department stores of Japan Japanese brands J. Front Retailing Japanese company stubs Retail company stubs Hidden categories: Articles with short description Short description is different from Wikidata Articles needing translation from Japanese Wikipedia Articles containing Japanese-language text Commons category link is on Wikidata All stub articles",
  "infobox": {
    "logo_url": "https://upload.wikimedia.org/wikipedia/commons/thumb/b/b9/Parco_logo.svg/220px-Parco_logo.svg.png",
    "name": "",
    "native_name": "株式会社パルコ",
    "company_type": "Subsidiary",
    "industry": "Retail",
    "founded": "Ikebukuro, Toshima, Tokyo , Japan February 13, 1953 ( 1953-02-13 )",
    "headquarters": "Shibuya First Place Building, 8-16, Shinsencho, Shibuya, Tokyo , Japan 1-28-2, Minami- Ikebukuro , Toshima, Tokyo , Japan (registered)",
    "number_of_locations": "17 stores (2023)",
    "key_people": "Kozo Makiyama (President)",
    "revenue": "¥ 264,840 million (FY2010) [ 1 ]",
    "operating_income": "¥ 9,218 million (FY2010) [ 1 ]",
    "net_income": "¥ 4,400 million (FY2010) [ 1 ]",
    "total_assets": "¥ 222,135 million (FY2010) [ 1 ]",
    "total_equity": "¥ 81,868 million (FY2010) [ 1 ]",
    "owner": "J. Front Retailing",
    "number_of_employees": "651 (directly) 2,208 (contract)",
    "website": "www .parco .co .jp /en /"
  },
  "company_name": "Unknown",
  "logo_url": "https://upload.wikimedia.org/wikipedia/commons/thumb/b/b9/Parco_logo.svg/220px-Parco_logo.svg.png"
}